shade_agent/__init__.py
shade_agent/api_wrapper.py
shade_agent_py-0.1.0.dist-info/METADATA
shade_agent_py-0.1.0.dist-info/WHEEL
shade_agent_py-0.1.0.dist-info/licenses/LICENSE
shade_agent_py-0.1.0.dist-info/RECORD
