Metadata-Version: 2.4
Name: shade-agent-py
Version: 0.1.0
Summary: A Python library for shade agent functionality
Author-email: Owen Hassall <owen@proximity.dev>
License: Copyright 2025 Proximity Labs 
License-File: LICENSE
Requires-Python: >=3.8
Requires-Dist: httpx>=0.28.1
